canvas_course_tools/__init__.py
canvas_course_tools/canvas_tasks.py
canvas_course_tools/cli.py
canvas_course_tools/configfile.py
canvas_course_tools/courses.py
canvas_course_tools/datatypes.py
canvas_course_tools/group_lists.py
canvas_course_tools/groups.py
canvas_course_tools/servers.py
canvas_course_tools/students.py
canvas_course_tools/templates/exam.tex
canvas_course_tools/templates/peer-feedback.tex
canvas_course_tools/templates/photos.tex
canvas_course_tools/templates/signatures.tex
canvas_course_tools/templates/student-list-pairs.tex
canvas_course_tools/templates/student-list.tex
canvas_course_tools/templates/student-list.txt
canvas_course_tools/templates/template-info.toml
canvas_course_tools/templates.py
canvas_course_tools/utils.py
canvas_course_tools-0.14.2.dist-info/WHEEL
canvas_course_tools-0.14.2.dist-info/entry_points.txt
canvas_course_tools-0.14.2.dist-info/METADATA
canvas_course_tools-0.14.2.dist-info/RECORD
