Metadata-Version: 2.4
Name: canvas-course-tools
Version: 0.14.2
Summary: Canvas course tools
Author: David Fokkema
Author-email: David Fokkema <davidfokkema@icloud.com>
License-Expression: GPL-3.0-or-later
Classifier: Development Status :: 5 - Production/Stable
Classifier: Environment :: Console
Classifier: Intended Audience :: Education
Classifier: Intended Audience :: End Users/Desktop
Classifier: License :: OSI Approved :: GNU General Public License v3 or later (GPLv3+)
Classifier: Operating System :: MacOS
Classifier: Operating System :: Microsoft :: Windows
Classifier: Operating System :: POSIX
Classifier: Programming Language :: Python
Requires-Dist: click>=8.2.1
Requires-Dist: httpx>=0.28.1
Requires-Dist: jinja2>=3.1.6
Requires-Dist: platformdirs>=4.3.8
Requires-Dist: pydantic>=2.11.7
Requires-Dist: rich>=14.0.0
Requires-Dist: rich-click>=1.8.9
Requires-Dist: tomli-w>=1.2.0
Requires-Dist: trogon>=0.6.0
Requires-Python: >=3.11
Project-URL: Homepage, https://github.com/davidfokkema/canvas-course-tools
Project-URL: Documentation, https://github.com/davidfokkema/canvas-course-tools/blob/main/README.md
Project-URL: Repository, https://github.com/davidfokkema/canvas-course-tools.git
Project-URL: Issues, https://github.com/davidfokkema/canvas-course-tools/issues
Project-URL: Changelog, https://github.com/davidfokkema/canvas-course-tools/blob/main/CHANGELOG.md
